{"nodes": [{"nodeID": "341345", "text": "A successful start to the year: Volkswagen brand continues upward trend", "type": "I", "timestamp": "2018-05-11 09:31:16"}, {"nodeID": "341348", "text": "Pace of model and innovation offensive stepped up", "type": "I", "timestamp": "2018-05-11 09:31:17"}, {"nodeID": "341362", "text": "\"Our long-term goal is clear: we want to make Volkswagen fit for the future of mobility.\"", "type": "I", "timestamp": "2018-05-14 07:08:35"}, {"nodeID": "341384", "text": "The brand forged ahead with the implementation of the upcoming electric offensive in the first three months of the year.", "type": "I", "timestamp": "2018-05-14 07:24:59"}, {"nodeID": "341386", "text": "\"We will continue to invest strongly in the future of the brand, especially in the major model and innovation offensive.\"", "type": "I", "timestamp": "2018-05-14 07:24:59"}, {"nodeID": "341390", "text": "In the 2018 financial year, deliveries, sales revenue and operating result will continue to rise, among other things as a result of the further implementation of the pact for the future and the turnaround programs in the regions.", "type": "I", "timestamp": "2018-05-14 07:25:00"}, {"nodeID": "341399", "text": "In the course of its TRANSFORM 2025+ strategy, the brand will renew its entire model range by 2020 as well as expanding it in key segments. From 2020, the newly developed I.D. family will start the brand's major electric offensive.", "type": "I", "timestamp": "2018-05-14 07:25:01"}, {"nodeID": "341536", "text": "Default Inference", "type": "RA", "timestamp": "2018-05-14 17:12:01", "scheme": "Default Inference", "schemeID": "72"}, {"nodeID": "341537", "text": "Default Inference", "type": "RA", "timestamp": "2018-05-14 17:12:01", "scheme": "Default Inference", "schemeID": "72"}, {"nodeID": "341538", "text": "Default Inference", "type": "RA", "timestamp": "2018-05-14 17:12:01", "scheme": "Default Inference", "schemeID": "72"}, {"nodeID": "341539", "text": "Default Inference", "type": "RA", "timestamp": "2018-05-14 17:12:02", "scheme": "Default Inference", "schemeID": "72"}, {"nodeID": "341540", "text": "Default Inference", "type": "RA", "timestamp": "2018-05-14 17:12:02", "scheme": "Default Inference", "schemeID": "72"}, {"nodeID": "341541", "text": "Default Inference", "type": "RA", "timestamp": "2018-05-14 17:12:02", "scheme": "Default Inference", "schemeID": "72"}], "edges": [{"edgeID": "427345", "fromID": "341348", "toID": "341536", "formEdgeID": null}, {"edgeID": "427346", "fromID": "341536", "toID": "341345", "formEdgeID": null}, {"edgeID": "427347", "fromID": "341362", "toID": "341537", "formEdgeID": null}, {"edgeID": "427348", "fromID": "341537", "toID": "341348", "formEdgeID": null}, {"edgeID": "427349", "fromID": "341384", "toID": "341538", "formEdgeID": null}, {"edgeID": "427350", "fromID": "341538", "toID": "341362", "formEdgeID": null}, {"edgeID": "427351", "fromID": "341386", "toID": "341539", "formEdgeID": null}, {"edgeID": "427352", "fromID": "341539", "toID": "341384", "formEdgeID": null}, {"edgeID": "427353", "fromID": "341390", "toID": "341540", "formEdgeID": null}, {"edgeID": "427354", "fromID": "341540", "toID": "341348", "formEdgeID": null}, {"edgeID": "427355", "fromID": "341399", "toID": "341541", "formEdgeID": null}, {"edgeID": "427356", "fromID": "341541", "toID": "341386", "formEdgeID": null}], "locutions": []}