{"nodes": [{"nodeID": "48265", "text": "Blueberries. Fresh or frozen, these tinysuperfruits\u00a0pack a big antioxidant punch", "type": "I", "timestamp": "2015-03-05 15:25:47"}, {"nodeID": "48266", "text": "Studies suggest that eating blueberries regularly can help improve everything from memory and motor skills to blood pressure and metabolism.", "type": "I", "timestamp": "2015-03-05 15:25:47"}, {"nodeID": "48267", "text": "Positive Consequences", "type": "RA", "timestamp": "2015-03-05 15:25:47", "scheme": "PositiveConsequences", "schemeID": "27"}], "edges": [{"edgeID": "65501", "fromID": "48266", "toID": "48267", "formEdgeID": null}, {"edgeID": "65502", "fromID": "48267", "toID": "48265", "formEdgeID": null}], "locutions": []}